qwenvpfcode_ai/__init__.py
qwenvpfcode_ai/cli.py
qwenvpfcode_ai/config.py
qwenvpfcode_ai/memory.py
qwenvpfcode_ai/model.py
qwenvpfcode_ai/utils.py
qwenvpfcode_ai-1.0.0.dist-info/licenses/LICENSE
qwenvpfcode_ai-1.0.0.dist-info/METADATA
qwenvpfcode_ai-1.0.0.dist-info/WHEEL
qwenvpfcode_ai-1.0.0.dist-info/entry_points.txt
qwenvpfcode_ai-1.0.0.dist-info/top_level.txt
qwenvpfcode_ai-1.0.0.dist-info/RECORD
