Metadata-Version: 2.4
Name: qwenvpfcode-ai
Version: 1.0.0
Summary: Fast local AI assistant based on Qwen2.5-Coder-1.5B - No filters, complete memory
Home-page: https://github.com/litaliano00-dev/QwenVPFCode-AI
Author: Adriano (litaliano00-dev)
Author-email: Adriano <litaliano00.contact@gmail.com>
License: MIT
Project-URL: Homepage, https://github.com/litaliano00-dev/QwenVPFCode-AI
Project-URL: Bug-Tracker, https://github.com/litaliano00-dev/QwenVPFCode-AI/issues
Project-URL: Source, https://github.com/litaliano00-dev/QwenVPFCode-AI
Keywords: ai,local-ai,qwen,assistant,terminal,uncensored,privacy
Requires-Python: >=3.8
License-File: LICENSE
Dynamic: author
Dynamic: home-page
Dynamic: license-file
Dynamic: requires-python
